{"cameraMode":{"drawMode":0,"name":"Shaded","section":"Shading Mode"},"sceneLighting":false,"audioPlay":false,"sceneViewState":{"m_AlwaysRefresh":false,"showFog":true,"showSkybox":false,"showFlares":true,"showImageEffects":true,"showParticleSystems":true,"showVisualEffectGraphs":true,"m_FxEnabled":true},"in2DMode":false,"pivot":{"x":100.0,"y":0.0,"z":0.0},"rotation":{"x":-0.036895494908094409,"y":-0.1774289309978485,"z":-0.006656840443611145,"w":0.9834204316139221},"size":122.06555938720703,"orthographic":true}